code_doc_gen/__init__.py
code_doc_gen/ai_analyzer.py
code_doc_gen/analyzer.py
code_doc_gen/ast_analyzer.py
code_doc_gen/config.py
code_doc_gen/generator.py
code_doc_gen/git_integration.py
code_doc_gen/main.py
code_doc_gen/models.py
code_doc_gen/scanner.py
code_doc_gen/parsers/__init__.py
code_doc_gen/parsers/cpp_parser.py
code_doc_gen/parsers/java_parser.py
code_doc_gen/parsers/javascript_parser.py
code_doc_gen/parsers/python_parser.py
code_doc_gen-1.2.0.dist-info/licenses/LICENSE
tests/__init__.py
tests/test_ai_analyzer.py
tests/test_analyzer.py
tests/test_generator.py
tests/test_git_integration.py
tests/test_java_parser.py
tests/test_javascript_parser.py
code_doc_gen-1.2.0.dist-info/METADATA
code_doc_gen-1.2.0.dist-info/WHEEL
code_doc_gen-1.2.0.dist-info/entry_points.txt
code_doc_gen-1.2.0.dist-info/top_level.txt
code_doc_gen-1.2.0.dist-info/RECORD
