Metadata-Version: 2.4
Name: code_doc_gen
Version: 1.2.0
Summary: Intelligent automatic documentation generation for Python and C++ codebases using AST analysis and NLTK
Home-page: https://github.com/mohitmishra786/CodeDocGen
Author: Mohit Mishra
Author-email: mohitmishra786687@gmail.com
Project-URL: Bug Reports, https://github.com/mohitmishra786/CodeDocGen/issues
Project-URL: Source, https://github.com/mohitmishra786/CodeDocGen
Project-URL: Documentation, https://github.com/mohitmishra786/CodeDocGen#readme
Keywords: documentation,code-generation,nltk,ast,parser,c++,python,doxygen,docstring
Classifier: Development Status :: 4 - Beta
Classifier: Intended Audience :: Developers
Classifier: License :: OSI Approved :: MIT License
Classifier: Operating System :: OS Independent
Classifier: Programming Language :: Python :: 3
Classifier: Programming Language :: Python :: 3.8
Classifier: Programming Language :: Python :: 3.9
Classifier: Programming Language :: Python :: 3.10
Classifier: Programming Language :: Python :: 3.11
Classifier: Programming Language :: Python :: 3.12
Classifier: Topic :: Software Development :: Documentation
Classifier: Topic :: Software Development :: Libraries :: Python Modules
Classifier: Topic :: Text Processing :: Linguistic
Requires-Python: >=3.8
License-File: LICENSE
Requires-Dist: nltk>=3.8
Requires-Dist: pyyaml>=6.0
Requires-Dist: pytest>=7.0.0
Requires-Dist: typing-extensions>=4.0.0
Requires-Dist: python-dotenv>=1.0.0
Provides-Extra: dev
Requires-Dist: pytest>=7.0.0; extra == "dev"
Requires-Dist: pytest-cov>=4.0.0; extra == "dev"
Requires-Dist: black>=22.0.0; extra == "dev"
Requires-Dist: flake8>=5.0.0; extra == "dev"
Requires-Dist: mypy>=1.0.0; extra == "dev"
Provides-Extra: test
Requires-Dist: pytest>=7.0.0; extra == "test"
Requires-Dist: pytest-cov>=4.0.0; extra == "test"
Provides-Extra: cpp
Requires-Dist: clang>=6.0.0; extra == "cpp"
Provides-Extra: ai
Requires-Dist: groq>=0.4.0; extra == "ai"
Requires-Dist: openai>=1.0.0; extra == "ai"
Provides-Extra: all
Requires-Dist: clang>=6.0.0; extra == "all"
Requires-Dist: groq>=0.4.0; extra == "all"
Requires-Dist: openai>=1.0.0; extra == "all"
Dynamic: author
Dynamic: author-email
Dynamic: classifier
Dynamic: description
Dynamic: description-content-type
Dynamic: home-page
Dynamic: keywords
Dynamic: license-file
Dynamic: project-url
Dynamic: provides-extra
Dynamic: requires-dist
Dynamic: requires-python
Dynamic: summary
